{
	"nodes": [
		{
			"width": 170,
			"height": 122,
			"id": "Agama-rrf-Node-b8a493f4-dc03-4fba-9cd4-bf824b6f8cc2",
			"position": {
				"x": 718.6839797344921,
				"y": 206.52501407326935
			},
			"type": "rrf",
			"data": {
				"id": "Agama-rrf-Node-b8a493f4-dc03-4fba-9cd4-bf824b6f8cc2",
				"type": "Agama-rrf-Node",
				"parentId": "Agama-repeat-Node-fafdc9a3-ed1b-48a2-a763-509c13a4735f",
				"whenCondition": "",
				"inRepeatBlock": false,
				"position": {
					"x": 718.6839797344921,
					"y": 206.52501407326935
				},
				"agamaData": {
					"id": "Agama-rrf-Node-b8a493f4-dc03-4fba-9cd4-bf824b6f8cc2",
					"parentId": "Agama-repeat-Node-fafdc9a3-ed1b-48a2-a763-509c13a4735f",
					"type": "Agama-rrf-Node",
					"displayName": "UserName ",
					"hasComment": true,
					"comment": "",
					"whenCondition": "",
					"inRepeatBlock": false,
					"assignments": [],
					"nodeIcon": "ph:globe-simple",
					"templatePath": "username.ftlh",
					"asssignedVariableName": "creds",
					"arguments": "authResult"
				},
				"skake": false
			},
			"selected": false,
			"dragging": false,
			"positionAbsolute": {
				"x": 718.6839797344921,
				"y": 206.52501407326935
			}
		},
		{
			"width": 170,
			"height": 122,
			"id": "Agama-assignment-Node-aba991ea-29db-4eec-9f10-e9e3bc0e253f",
			"position": {
				"x": 963.6839797344921,
				"y": 436.52501407326935
			},
			"type": "assignment",
			"data": {
				"id": "Agama-assignment-Node-aba991ea-29db-4eec-9f10-e9e3bc0e253f",
				"type": "Agama-assignment-Node",
				"parentId": "Agama-call-Node-1d688a4e-9848-4e59-ae83-e279c4d61436",
				"whenCondition": "",
				"inRepeatBlock": true,
				"position": {
					"x": 963.6839797344921,
					"y": 436.52501407326935
				},
				"agamaData": {
					"id": "Agama-assignment-Node-aba991ea-29db-4eec-9f10-e9e3bc0e253f",
					"parentId": "Agama-call-Node-1d688a4e-9848-4e59-ae83-e279c4d61436",
					"type": "Agama-assignment-Node",
					"displayName": "uid",
					"hasComment": true,
					"comment": "",
					"whenCondition": "",
					"inRepeatBlock": true,
					"assignments": [
						{
							"variableTypeCheck": false,
							"assignmentExpression": "creds.username",
							"assignedVariableName": "authResult.uid"
						}
					],
					"nodeIcon": "material-symbols:equal"
				},
				"skake": false
			},
			"selected": false,
			"dragging": false,
			"positionAbsolute": {
				"x": 963.6839797344921,
				"y": 436.52501407326935
			}
		},
		{
			"width": 170,
			"height": 122,
			"id": "Agama-call-Node-1d688a4e-9848-4e59-ae83-e279c4d61436",
			"position": {
				"x": 765.6839797344921,
				"y": 436.52501407326935
			},
			"type": "call",
			"data": {
				"id": "Agama-call-Node-1d688a4e-9848-4e59-ae83-e279c4d61436",
				"type": "Agama-call-Node",
				"parentId": "Agama-rrf-Node-26edb9ca-364a-4ba0-983a-6bf78eb870b5",
				"whenCondition": "",
				"inRepeatBlock": true,
				"position": {
					"x": 765.6839797344921,
					"y": 436.52501407326935
				},
				"agamaData": {
					"id": "Agama-call-Node-1d688a4e-9848-4e59-ae83-e279c4d61436",
					"parentId": "Agama-rrf-Node-26edb9ca-364a-4ba0-983a-6bf78eb870b5",
					"type": "Agama-call-Node",
					"displayName": "validate credentials",
					"hasComment": true,
					"comment": "",
					"javaClassName": "",
					"javaMethodName": "authenticate",
					"javaVariableName": "authServiceCdiUtil",
					"exceptionVariableField": "",
					"callType": "Call method on instance",
					"whenCondition": "",
					"inRepeatBlock": true,
					"arguments": [
						"creds.username",
						"creds.password"
					],
					"nodeIcon": "material-symbols:code",
					"asssignedVariableName": "authResult.success"
				},
				"skake": false
			},
			"selected": false,
			"dragging": false,
			"positionAbsolute": {
				"x": 765.6839797344921,
				"y": 436.52501407326935
			}
		},
		{
			"width": 170,
			"height": 122,
			"id": "Agama-rrf-Node-26edb9ca-364a-4ba0-983a-6bf78eb870b5",
			"position": {
				"x": 563.6839797344921,
				"y": 436.52501407326935
			},
			"type": "rrf",
			"data": {
				"id": "Agama-rrf-Node-26edb9ca-364a-4ba0-983a-6bf78eb870b5",
				"type": "Agama-rrf-Node",
				"parentId": "Agama-repeat-Node-fafdc9a3-ed1b-48a2-a763-509c13a4735f",
				"whenCondition": "",
				"inRepeatBlock": true,
				"position": {
					"x": 563.6839797344921,
					"y": 436.52501407326935
				},
				"agamaData": {
					"id": "Agama-rrf-Node-26edb9ca-364a-4ba0-983a-6bf78eb870b5",
					"parentId": "Agama-repeat-Node-fafdc9a3-ed1b-48a2-a763-509c13a4735f",
					"type": "Agama-rrf-Node",
					"displayName": "Login page",
					"hasComment": true,
					"comment": "",
					"whenCondition": "",
					"inRepeatBlock": true,
					"assignments": [],
					"nodeIcon": "ph:globe-simple",
					"templatePath": "login.ftlh",
					"asssignedVariableName": "creds",
					"arguments": [
						"authResult"
					]
				},
				"skake": false
			},
			"selected": false,
			"dragging": false,
			"positionAbsolute": {
				"x": 563.6839797344921,
				"y": 436.52501407326935
			}
		},
		{
			"width": 170,
			"height": 122,
			"id": "Agama-repeat-Node-fafdc9a3-ed1b-48a2-a763-509c13a4735f",
			"position": {
				"x": 468.6839797344922,
				"y": 206.52501407326935
			},
			"type": "repeat",
			"data": {
				"id": "Agama-repeat-Node-fafdc9a3-ed1b-48a2-a763-509c13a4735f",
				"type": "Agama-repeat-Node",
				"parentId": "Agama-assignment-Node-cfc36e09-9ced-4717-9c18-54dcc7c35507",
				"whenCondition": "",
				"inRepeatBlock": false,
				"handles": [],
				"position": {
					"x": 468.6839797344922,
					"y": 206.52501407326935
				},
				"agamaData": {
					"id": "Agama-repeat-Node-fafdc9a3-ed1b-48a2-a763-509c13a4735f",
					"parentId": "Agama-assignment-Node-cfc36e09-9ced-4717-9c18-54dcc7c35507",
					"type": "Agama-repeat-Node",
					"displayName": "Max re-try",
					"hasComment": true,
					"comment": "",
					"whenCondition": "",
					"inRepeatBlock": false,
					"nodeIcon": "material-symbols:event-repeat-outline-rounded",
					"maxIteration": "3",
					"maxIterationVariableName": ""
				},
				"skake": false
			},
			"selected": false,
			"dragging": false,
			"positionAbsolute": {
				"x": 468.6839797344922,
				"y": 206.52501407326935
			}
		},
		{
			"width": 170,
			"height": 122,
			"id": "Agama-assignment-Node-cfc36e09-9ced-4717-9c18-54dcc7c35507",
			"position": {
				"x": 268.6839797344922,
				"y": 206.52501407326935
			},
			"type": "assignment",
			"data": {
				"id": "Agama-assignment-Node-cfc36e09-9ced-4717-9c18-54dcc7c35507",
				"type": "Agama-assignment-Node",
				"parentId": "Agama-call-Node-3c658c27-1a91-497a-9fc2-823b73d63d96",
				"whenCondition": "",
				"inRepeatBlock": false,
				"position": {
					"x": 268.6839797344922,
					"y": 206.52501407326935
				},
				"agamaData": {
					"id": "Agama-assignment-Node-cfc36e09-9ced-4717-9c18-54dcc7c35507",
					"parentId": "Agama-call-Node-3c658c27-1a91-497a-9fc2-823b73d63d96",
					"type": "Agama-assignment-Node",
					"displayName": "Auth Result",
					"hasComment": true,
					"comment": "",
					"whenCondition": "",
					"inRepeatBlock": false,
					"assignments": [
						{
							"variableTypeCheck": false,
							"assignmentExpression": "{}",
							"assignedVariableName": "authResult"
						}
					],
					"nodeIcon": "material-symbols:equal"
				},
				"skake": false
			},
			"selected": false,
			"dragging": false,
			"positionAbsolute": {
				"x": 268.6839797344922,
				"y": 206.52501407326935
			}
		},
		{
			"width": 170,
			"height": 122,
			"id": "Agama-call-Node-3c658c27-1a91-497a-9fc2-823b73d63d96",
			"position": {
				"x": 30.981000562930774,
				"y": 199.3920180137847
			},
			"type": "call",
			"data": {
				"id": "Agama-call-Node-3c658c27-1a91-497a-9fc2-823b73d63d96",
				"type": "Agama-call-Node",
				"parentId": "Agama-call-Node-8600d432-1797-451e-824b-16e1b6e23d37",
				"whenCondition": "",
				"inRepeatBlock": false,
				"position": {
					"x": 30.981000562930774,
					"y": 199.3920180137847
				},
				"agamaData": {
					"id": "Agama-call-Node-3c658c27-1a91-497a-9fc2-823b73d63d96",
					"parentId": "Agama-call-Node-8600d432-1797-451e-824b-16e1b6e23d37",
					"type": "Agama-call-Node",
					"displayName": "CdiUtil(Auth service)",
					"hasComment": true,
					"comment": "",
					"javaClassName": "io.jans.service.cdi.util.CdiUtil",
					"javaMethodName": "bean",
					"javaVariableName": "",
					"exceptionVariableField": "",
					"callType": "Call static method",
					"whenCondition": "",
					"inRepeatBlock": false,
					"arguments": [
						"authService"
					],
					"nodeIcon": "material-symbols:code",
					"asssignedVariableName": "authServiceCdiUtil"
				},
				"skake": false
			},
			"selected": false,
			"dragging": false,
			"positionAbsolute": {
				"x": 30.981000562930774,
				"y": 199.3920180137847
			}
		},
		{
			"width": 170,
			"height": 122,
			"id": "Agama-call-Node-8600d432-1797-451e-824b-16e1b6e23d37",
			"position": {
				"x": 830,
				"y": 30
			},
			"type": "call",
			"data": {
				"id": "Agama-call-Node-8600d432-1797-451e-824b-16e1b6e23d37",
				"type": "Agama-call-Node",
				"parentId": "Agama-call-Node-f643ca0b-c51d-4447-9cfc-7f01d4510d81",
				"whenCondition": "",
				"inRepeatBlock": false,
				"position": {
					"x": 830,
					"y": 30
				},
				"agamaData": {
					"id": "Agama-call-Node-8600d432-1797-451e-824b-16e1b6e23d37",
					"parentId": "Agama-call-Node-f643ca0b-c51d-4447-9cfc-7f01d4510d81",
					"type": "Agama-call-Node",
					"displayName": "Identity Service",
					"hasComment": true,
					"comment": "",
					"javaClassName": "io.jans.as.server.security.Identity",
					"javaMethodName": "class",
					"javaVariableName": "",
					"exceptionVariableField": "",
					"callType": "Call static method",
					"whenCondition": "",
					"inRepeatBlock": false,
					"arguments": [],
					"nodeIcon": "material-symbols:code",
					"asssignedVariableName": "identity"
				},
				"skake": false
			},
			"selected": false,
			"dragging": false,
			"positionAbsolute": {
				"x": 830,
				"y": 30
			}
		},
		{
			"width": 170,
			"height": 122,
			"id": "Agama-call-Node-f643ca0b-c51d-4447-9cfc-7f01d4510d81",
			"position": {
				"x": 630,
				"y": 30
			},
			"type": "call",
			"data": {
				"id": "Agama-call-Node-f643ca0b-c51d-4447-9cfc-7f01d4510d81",
				"type": "Agama-call-Node",
				"parentId": "Agama-call-Node-efbfe2a1-0883-4a02-ba88-f3fd94983953",
				"whenCondition": "",
				"inRepeatBlock": false,
				"position": {
					"x": 630,
					"y": 30
				},
				"agamaData": {
					"id": "Agama-call-Node-f643ca0b-c51d-4447-9cfc-7f01d4510d81",
					"parentId": "Agama-call-Node-efbfe2a1-0883-4a02-ba88-f3fd94983953",
					"type": "Agama-call-Node",
					"displayName": "User service",
					"hasComment": true,
					"comment": "",
					"javaClassName": "io.jans.as.server.service.UserService",
					"javaMethodName": "class",
					"javaVariableName": "",
					"exceptionVariableField": "",
					"callType": "Call static method",
					"whenCondition": "",
					"inRepeatBlock": false,
					"arguments": [],
					"nodeIcon": "material-symbols:code",
					"asssignedVariableName": "userService"
				},
				"skake": false
			},
			"selected": false,
			"dragging": false,
			"positionAbsolute": {
				"x": 630,
				"y": 30
			}
		},
		{
			"width": 170,
			"height": 122,
			"id": "Agama-call-Node-efbfe2a1-0883-4a02-ba88-f3fd94983953",
			"position": {
				"x": 430,
				"y": 30
			},
			"type": "call",
			"data": {
				"id": "Agama-call-Node-efbfe2a1-0883-4a02-ba88-f3fd94983953",
				"type": "Agama-call-Node",
				"parentId": "Agama-log-Node-5a1a73b3-dd6c-4220-9f6b-ac3a850fb4f0",
				"whenCondition": "",
				"inRepeatBlock": false,
				"position": {
					"x": 430,
					"y": 30
				},
				"agamaData": {
					"id": "Agama-call-Node-efbfe2a1-0883-4a02-ba88-f3fd94983953",
					"parentId": "Agama-log-Node-5a1a73b3-dd6c-4220-9f6b-ac3a850fb4f0",
					"type": "Agama-call-Node",
					"displayName": "Auth Service",
					"hasComment": true,
					"comment": "",
					"javaClassName": "io.jans.as.server.service.AuthenticationService",
					"javaMethodName": "class",
					"javaVariableName": "",
					"exceptionVariableField": "",
					"callType": "Call static method",
					"whenCondition": "",
					"inRepeatBlock": false,
					"arguments": [],
					"nodeIcon": "material-symbols:code",
					"asssignedVariableName": "authService"
				},
				"skake": false
			},
			"selected": false,
			"dragging": false,
			"positionAbsolute": {
				"x": 430,
				"y": 30
			}
		},
		{
			"width": 170,
			"height": 122,
			"id": "Agama-log-Node-5a1a73b3-dd6c-4220-9f6b-ac3a850fb4f0",
			"position": {
				"x": 230,
				"y": 30
			},
			"type": "log",
			"data": {
				"id": "Agama-log-Node-5a1a73b3-dd6c-4220-9f6b-ac3a850fb4f0",
				"type": "Agama-log-Node",
				"parentId": "Agama-start-Flow-bbd0dc7b-9718-4854-8d3d-90d6e7bcb203",
				"whenCondition": "",
				"inRepeatBlock": false,
				"position": {
					"x": 230,
					"y": 30
				},
				"agamaData": {
					"id": "Agama-log-Node-5a1a73b3-dd6c-4220-9f6b-ac3a850fb4f0",
					"parentId": "Agama-start-Flow-bbd0dc7b-9718-4854-8d3d-90d6e7bcb203",
					"type": "Agama-log-Node",
					"displayName": "Import library",
					"hasComment": true,
					"comment": "",
					"whenCondition": "",
					"inRepeatBlock": false,
					"logMessage": "\"Necessary library import\"",
					"logLevel": "info",
					"nodeIcon": "octicon:log-16"
				},
				"skake": false
			},
			"selected": false,
			"dragging": false,
			"positionAbsolute": {
				"x": 230,
				"y": 30
			}
		},
		{
			"width": 170,
			"height": 122,
			"id": "Agama-start-Flow-bbd0dc7b-9718-4854-8d3d-90d6e7bcb203",
			"type": "start",
			"sourcePosition": "right",
			"data": {
				"id": "Agama-start-Flow-bbd0dc7b-9718-4854-8d3d-90d6e7bcb203",
				"type": "Agama-start-Flow",
				"position": {
					"x": 30,
					"y": 30
				},
				"inRepeatBlock": false,
				"agamaData": {
					"id": "Agama-start-Flow-bbd0dc7b-9718-4854-8d3d-90d6e7bcb203",
					"type": "Agama-start-Flow",
					"displayName": "Password reset",
					"hasComment": true,
					"comment": "",
					"isTopLevelFlow": true,
					"basepath": "",
					"configParams": "{}",
					"nodeIcon": "material-symbols:line-start-square",
					"timeout": "",
					"inputs": "",
					"configs": "",
					"flowname": "agama.pw.reset"
				},
				"skake": false
			},
			"position": {
				"x": 30,
				"y": 30
			},
			"selected": false,
			"dragging": false,
			"positionAbsolute": {
				"x": 30,
				"y": 30
			}
		}
	],
	"edges": [
		{
			"id": "Agama-start-Flow-bbd0dc7b-9718-4854-8d3d-90d6e7bcb203-Agama-log-Node-5a1a73b3-dd6c-4220-9f6b-ac3a850fb4f0-d5d26b21-3fce-45ea-ab3a-229aaf8cd7af",
			"type": "straight",
			"source": "Agama-start-Flow-bbd0dc7b-9718-4854-8d3d-90d6e7bcb203",
			"target": "Agama-log-Node-5a1a73b3-dd6c-4220-9f6b-ac3a850fb4f0",
			"label": "",
			"labelBgPadding": [
				8,
				4
			],
			"labelBgBorderRadius": 4,
			"labelBgStyle": {
				"fill": "#FFCC00",
				"color": "#fff",
				"fillOpacity": 0.7
			}
		},
		{
			"id": "Agama-log-Node-5a1a73b3-dd6c-4220-9f6b-ac3a850fb4f0-Agama-call-Node-efbfe2a1-0883-4a02-ba88-f3fd94983953-b38c8f00-eab9-4f1f-a470-2fdd04a45f5f",
			"type": "straight",
			"source": "Agama-log-Node-5a1a73b3-dd6c-4220-9f6b-ac3a850fb4f0",
			"target": "Agama-call-Node-efbfe2a1-0883-4a02-ba88-f3fd94983953",
			"label": "",
			"labelBgPadding": [
				8,
				4
			],
			"labelBgBorderRadius": 4,
			"labelBgStyle": {
				"fill": "#FFCC00",
				"color": "#fff",
				"fillOpacity": 0.7
			}
		},
		{
			"id": "Agama-call-Node-efbfe2a1-0883-4a02-ba88-f3fd94983953-Agama-call-Node-f643ca0b-c51d-4447-9cfc-7f01d4510d81-3460e618-d6cd-4f7a-95a3-d888f3a210e5",
			"type": "straight",
			"source": "Agama-call-Node-efbfe2a1-0883-4a02-ba88-f3fd94983953",
			"target": "Agama-call-Node-f643ca0b-c51d-4447-9cfc-7f01d4510d81",
			"label": "",
			"labelBgPadding": [
				8,
				4
			],
			"labelBgBorderRadius": 4,
			"labelBgStyle": {
				"fill": "#FFCC00",
				"color": "#fff",
				"fillOpacity": 0.7
			}
		},
		{
			"id": "Agama-call-Node-f643ca0b-c51d-4447-9cfc-7f01d4510d81-Agama-call-Node-8600d432-1797-451e-824b-16e1b6e23d37-3c09ed1a-4366-4fc4-846a-18ab644551e1",
			"type": "straight",
			"source": "Agama-call-Node-f643ca0b-c51d-4447-9cfc-7f01d4510d81",
			"target": "Agama-call-Node-8600d432-1797-451e-824b-16e1b6e23d37",
			"label": "",
			"labelBgPadding": [
				8,
				4
			],
			"labelBgBorderRadius": 4,
			"labelBgStyle": {
				"fill": "#FFCC00",
				"color": "#fff",
				"fillOpacity": 0.7
			}
		},
		{
			"id": "Agama-call-Node-8600d432-1797-451e-824b-16e1b6e23d37-Agama-call-Node-3c658c27-1a91-497a-9fc2-823b73d63d96-6391837e-9900-4740-a005-595c70b04907",
			"type": "straight",
			"source": "Agama-call-Node-8600d432-1797-451e-824b-16e1b6e23d37",
			"target": "Agama-call-Node-3c658c27-1a91-497a-9fc2-823b73d63d96",
			"label": "",
			"labelBgPadding": [
				8,
				4
			],
			"labelBgBorderRadius": 4,
			"labelBgStyle": {
				"fill": "#FFCC00",
				"color": "#fff",
				"fillOpacity": 0.7
			}
		},
		{
			"id": "Agama-call-Node-3c658c27-1a91-497a-9fc2-823b73d63d96-Agama-assignment-Node-cfc36e09-9ced-4717-9c18-54dcc7c35507-c644ab7c-21c5-483c-9658-df7bf6b60924",
			"type": "straight",
			"source": "Agama-call-Node-3c658c27-1a91-497a-9fc2-823b73d63d96",
			"target": "Agama-assignment-Node-cfc36e09-9ced-4717-9c18-54dcc7c35507",
			"label": "",
			"labelBgPadding": [
				8,
				4
			],
			"labelBgBorderRadius": 4,
			"labelBgStyle": {
				"fill": "#FFCC00",
				"color": "#fff",
				"fillOpacity": 0.7
			}
		},
		{
			"id": "Agama-assignment-Node-cfc36e09-9ced-4717-9c18-54dcc7c35507-Agama-repeat-Node-fafdc9a3-ed1b-48a2-a763-509c13a4735f-919442a6-d857-451e-8930-2cbcdc983034",
			"type": "straight",
			"source": "Agama-assignment-Node-cfc36e09-9ced-4717-9c18-54dcc7c35507",
			"target": "Agama-repeat-Node-fafdc9a3-ed1b-48a2-a763-509c13a4735f",
			"label": "",
			"labelBgPadding": [
				8,
				4
			],
			"labelBgBorderRadius": 4,
			"labelBgStyle": {
				"fill": "#FFCC00",
				"color": "#fff",
				"fillOpacity": 0.7
			}
		},
		{
			"id": "Agama-repeat-Node-fafdc9a3-ed1b-48a2-a763-509c13a4735f-Agama-rrf-Node-26edb9ca-364a-4ba0-983a-6bf78eb870b5-5006c228-efc9-468c-96cd-646ad4891319",
			"type": "straight",
			"source": "Agama-repeat-Node-fafdc9a3-ed1b-48a2-a763-509c13a4735f",
			"target": "Agama-rrf-Node-26edb9ca-364a-4ba0-983a-6bf78eb870b5",
			"label": "In Block",
			"labelBgPadding": [
				8,
				4
			],
			"labelBgBorderRadius": 4,
			"labelBgStyle": {
				"fill": "#FFCC00",
				"color": "#fff",
				"fillOpacity": 0.7
			},
			"sourceHandle": "Agama-repeat-Node-fafdc9a3-ed1b-48a2-a763-509c13a4735f.InRepeatBlock"
		},
		{
			"id": "Agama-rrf-Node-26edb9ca-364a-4ba0-983a-6bf78eb870b5-Agama-call-Node-1d688a4e-9848-4e59-ae83-e279c4d61436-9bf93e1b-fa5b-4f4e-b9ab-a0381a8f8bdb",
			"type": "straight",
			"source": "Agama-rrf-Node-26edb9ca-364a-4ba0-983a-6bf78eb870b5",
			"target": "Agama-call-Node-1d688a4e-9848-4e59-ae83-e279c4d61436",
			"label": "",
			"labelBgPadding": [
				8,
				4
			],
			"labelBgBorderRadius": 4,
			"labelBgStyle": {
				"fill": "#FFCC00",
				"color": "#fff",
				"fillOpacity": 0.7
			}
		},
		{
			"id": "Agama-call-Node-1d688a4e-9848-4e59-ae83-e279c4d61436-Agama-assignment-Node-aba991ea-29db-4eec-9f10-e9e3bc0e253f-126df62b-a83e-4ec7-9f68-1757671774ed",
			"type": "straight",
			"source": "Agama-call-Node-1d688a4e-9848-4e59-ae83-e279c4d61436",
			"target": "Agama-assignment-Node-aba991ea-29db-4eec-9f10-e9e3bc0e253f",
			"label": "",
			"labelBgPadding": [
				8,
				4
			],
			"labelBgBorderRadius": 4,
			"labelBgStyle": {
				"fill": "#FFCC00",
				"color": "#fff",
				"fillOpacity": 0.7
			}
		},
		{
			"id": "Agama-assignment-Node-aba991ea-29db-4eec-9f10-e9e3bc0e253f-Agama-when-Node-38aeadae-d581-4e26-b97f-8a402247fbc5-525af973-8499-475b-b2dd-1c113f2143d8",
			"type": "straight",
			"source": "Agama-assignment-Node-aba991ea-29db-4eec-9f10-e9e3bc0e253f",
			"target": "Agama-when-Node-38aeadae-d581-4e26-b97f-8a402247fbc5",
			"label": "",
			"labelBgPadding": [
				8,
				4
			],
			"labelBgBorderRadius": 4,
			"labelBgStyle": {
				"fill": "#FFCC00",
				"color": "#fff",
				"fillOpacity": 0.7
			}
		},
		{
			"id": "Agama-assignment-Node-aba991ea-29db-4eec-9f10-e9e3bc0e253f-Agama-when-Node-d9362e8e-bdcb-47cc-a17b-f0ff959d3af3-d5df4d7c-6293-4ea7-8d47-6fd37c4886f2",
			"type": "straight",
			"source": "Agama-assignment-Node-aba991ea-29db-4eec-9f10-e9e3bc0e253f",
			"target": "Agama-when-Node-d9362e8e-bdcb-47cc-a17b-f0ff959d3af3",
			"label": "",
			"labelBgPadding": [
				8,
				4
			],
			"labelBgBorderRadius": 4,
			"labelBgStyle": {
				"fill": "#FFCC00",
				"color": "#fff",
				"fillOpacity": 0.7
			}
		},
		{
			"id": "Agama-when-Node-d9362e8e-bdcb-47cc-a17b-f0ff959d3af3-finish-49748e66-828f-447f-b625-358dea1116ed-6bf667f0-511a-4147-b36a-4f7fba33189f",
			"type": "straight",
			"source": "Agama-when-Node-d9362e8e-bdcb-47cc-a17b-f0ff959d3af3",
			"target": "finish-49748e66-828f-447f-b625-358dea1116ed",
			"label": "Condition met",
			"labelBgPadding": [
				8,
				4
			],
			"labelBgBorderRadius": 4,
			"labelBgStyle": {
				"fill": "#FFCC00",
				"color": "#fff",
				"fillOpacity": 0.7
			},
			"sourceHandle": "Agama-when-Node-d9362e8e-bdcb-47cc-a17b-f0ff959d3af3.SUCCESS"
		},
		{
			"id": "Agama-repeat-Node-fafdc9a3-ed1b-48a2-a763-509c13a4735f-Agama-rrf-Node-b8a493f4-dc03-4fba-9cd4-bf824b6f8cc2-58c02698-5565-4f16-b277-c7ed6439638d",
			"type": "straight",
			"source": "Agama-repeat-Node-fafdc9a3-ed1b-48a2-a763-509c13a4735f",
			"target": "Agama-rrf-Node-b8a493f4-dc03-4fba-9cd4-bf824b6f8cc2",
			"label": "Not In Block",
			"labelBgPadding": [
				8,
				4
			],
			"labelBgBorderRadius": 4,
			"labelBgStyle": {
				"fill": "#FFCC00",
				"color": "#fff",
				"fillOpacity": 0.7
			},
			"sourceHandle": "Agama-repeat-Node-fafdc9a3-ed1b-48a2-a763-509c13a4735f.InFlow"
		}
	],
	"viewport": {
		"x": 12.253326784486262,
		"y": 53.65451879454122,
		"zoom": 0.8467453123625271
	}
}